irsviz23/.DS_Store
irsviz23/2023gp.json
irsviz23/__init__.py
irsviz23/data.py
irsviz23/main.py
irsviz23/one_team.py
irsviz23/run_app.py
irsviz23/six_team_graph.py
irsviz23/total_points_graph.py
irsviz23/tests/.DS_Store
irsviz23/tests/__init__.py
irsviz23/tests/test_data.py
irsviz23/tests/inputs/pytest_viewer_data.json
irsviz23/tests/outputs/pytest_viewer_data.json
irsviz23-0.3.0.dist-info/entry_points.txt
irsviz23-0.3.0.dist-info/LICENSE
irsviz23-0.3.0.dist-info/WHEEL
irsviz23-0.3.0.dist-info/METADATA
irsviz23-0.3.0.dist-info/RECORD
